README.rst
setup.py
sphfile/__init__.py
sphfile/sphfile.py
sphfile.egg-info/PKG-INFO
sphfile.egg-info/SOURCES.txt
sphfile.egg-info/dependency_links.txt
sphfile.egg-info/top_level.txt
tests/__init__.py
tests/test_sample.py