Metadata-Version: 1.1
Name: sphfile
Version: 1.0.0
Summary: Numpy-based NIST SPH audio-file reader
Home-page: https://github.com/mcfletch/sphfile
Author: Mike C. Fletcher
Author-email: mcfletch@vrplumber.com
License: UNKNOWN
Platform: UNKNOWN
Classifier: Programming Language :: Python
Classifier: Programming Language :: Python :: 2
Classifier: Programming Language :: Python :: 2.7
Classifier: Programming Language :: Python :: 3
Classifier: Programming Language :: Python :: 3.4
Classifier: Programming Language :: Python :: 3.5
